acshell/__init__.py
acshell/acshell.py
acshell/cheatsheet.py
acshell/cheetsheet.py
acshell/consts.py
acshell/help.py
acshell/login.py
acshell/main.py
acshell/result.py
acshell/task_run.py
acshell/texts.py
acshell/utils.py
acshell/contest/__init__.py
acshell/contest/contest.py
acshell/contest/task.py
acshell-2.2.1.dist-info/LICENSE
acshell-2.2.1.dist-info/METADATA
acshell-2.2.1.dist-info/WHEEL
acshell-2.2.1.dist-info/entry_points.txt
acshell-2.2.1.dist-info/top_level.txt
acshell-2.2.1.dist-info/RECORD
