Metadata-Version: 2.1
Name: acshell
Version: 2.2.1
Summary: the commandline shell for python and pypy AtCoder user
Home-page: https://www.github.com/tani-cat/atcoder-shell
Author: tani-cat
License: MIT
Classifier: Environment :: Console
Classifier: Programming Language :: Python
Classifier: Programming Language :: Python :: 3
Classifier: Programming Language :: Python :: 3 :: Only
Classifier: Programming Language :: Python :: 3.8
Classifier: Programming Language :: Python :: 3.9
Classifier: Programming Language :: Python :: 3.10
Classifier: Programming Language :: Python :: 3.11
Requires-Python: >=3.8
License-File: LICENSE
Requires-Dist: appdirs (~=1.4.4)
Requires-Dist: beautifulsoup4 (~=4.11)
Requires-Dist: lxml (>=4.9)
Requires-Dist: requests (>=2.28)
Requires-Dist: tabulate (>=0.8.10)
